[
{"book_name": "周国平人生哲思录", "book_author": "作者：周国平", "book_file": "现代文学\\周国平人生哲思录.mobi", "book_url": "https://kgbook.com/e/DownSys/GetDown?classid=24&id=1149&pathid=0"},
{"book_name": "李自成", "book_author": "作者：姚雪垠", "book_file": "现代文学\\李自成.mobi", "book_url": "https://kgbook.com/e/DownSys/GetDown?classid=24&id=747&pathid=0"},
{"book_name": "北京北京", "book_author": "作者：冯唐", "book_file": "现代文学\\北京北京.pdf", "book_url": "https://kgbook.com/e/DownSys/GetDown?classid=24&id=471&pathid=0"},
{"book_name": "目光", "book_author": "作者：陶勇", "book_file": "现代文学\\目光.mobi", "book_url": "https://kgbook.com/e/DownSys/GetDown?classid=24&id=4742&pathid=0"},
{"book_name": "白鹿原", "book_author": "作者：陈忠实", "book_file": "现代文学\\白鹿原.mobi", "book_url": "https://kgbook.com/e/DownSys/GetDown?classid=24&id=245&pathid=0"},
{"book_name": "灵山", "book_author": "作者：高行健", "book_file": "现代文学\\灵山.pdf", "book_url": "https://kgbook.com/e/DownSys/GetDown?classid=24&id=940&pathid=0"},
{"book_name": "一个人的鲁迅系列", "book_author": "作者：林贤治", "book_file": "现代文学\\一个人的鲁迅系列.epub", "book_url": "https://kgbook.com/e/DownSys/GetDown?classid=24&id=1272&pathid=0"}
]